df_site/__init__.py
df_site/__main__.py
df_site/admin.py
df_site/apps.py
df_site/components/__init__.py
df_site/components/base.py
df_site/components/detail.py
df_site/components/list.py
df_site/components/list_filters.py
df_site/components/registry.py
df_site/constants.py
df_site/context_processors.py
df_site/defaults.py
df_site/dynamic_settings.py
df_site/form_fields.py
df_site/management/__init__.py
df_site/management/commands/__init__.py
df_site/management/commands/add_image.py
df_site/management/commands/generate_favicon.py
df_site/middleware.py
df_site/migrations/0001_initial.py
df_site/migrations/0002_alter_alertribbon_message_alter_alertribbon_summary.py
df_site/migrations/__init__.py
df_site/model_fields.py
df_site/models.py
df_site/postman/__init__.py
df_site/postman/forms.py
df_site/postman/urls.py
df_site/postman/views.py
df_site/static/css/app.css
df_site/static/css/base.css
df_site/static/css/ckeditor5.css
df_site/static/css/ckeditor5.css.map
df_site/static/favicon/android-chrome-192x192.png
df_site/static/favicon/android-chrome-512x512.png
df_site/static/favicon/apple-touch-icon.png
df_site/static/favicon/favicon-16x16.png
df_site/static/favicon/favicon-32x32.png
df_site/static/favicon/favicon.ico
df_site/static/favicon/mstile-150x150.png
df_site/static/favicon/safari-pinned-tab.svg
df_site/static/images/accessibility.svg
df_site/static/images/align-bottom.svg
df_site/static/images/align-center.svg
df_site/static/images/align-justify.svg
df_site/static/images/align-left.svg
df_site/static/images/align-middle.svg
df_site/static/images/align-right.svg
df_site/static/images/align-top.svg
df_site/static/images/bold.svg
df_site/static/images/browse-files.svg
df_site/static/images/bulletedlist.svg
df_site/static/images/cancel.svg
df_site/static/images/caption.svg
df_site/static/images/check.svg
df_site/static/images/code.svg
df_site/static/images/codeblock.svg
df_site/static/images/cog.svg
df_site/static/images/color-palette.svg
df_site-0.1.8.dist-info/LICENSE
df_site-0.1.8.dist-info/METADATA
df_site-0.1.8.dist-info/WHEEL
df_site-0.1.8.dist-info/entry_points.txt
df_site-0.1.8.dist-info/RECORD
