Metadata-Version: 2.3
Name: df_site
Version: 0.1.8
Summary: More batteries to Django
License: CECILL-B
Author: d9pouces
Author-email: github@19pouces.net
Maintainer: d9pouces
Maintainer-email: github@19pouces.net
Requires-Python: >=3.10,<4.0
Classifier: Development Status :: 5 - Production/Stable
Classifier: Framework :: Django :: 5.0
Classifier: License :: CeCILL-B Free Software License Agreement (CECILL-B)
Classifier: License :: OSI Approved :: CEA CNRS Inria Logiciel Libre License, version 2.1 (CeCILL-2.1)
Classifier: Natural Language :: English
Classifier: Natural Language :: French
Classifier: Operating System :: MacOS :: MacOS X
Classifier: Operating System :: POSIX :: BSD
Classifier: Operating System :: POSIX :: Linux
Classifier: Operating System :: Unix
Classifier: Programming Language :: Python :: 3
Classifier: Programming Language :: Python :: 3.10
Classifier: Programming Language :: Python :: 3.11
Classifier: Programming Language :: Python :: 3.12
Classifier: Programming Language :: Python :: 3.13
Classifier: Programming Language :: Python :: 3 :: Only
Requires-Dist: df-config (>=1.2.42)
Requires-Dist: df-websockets (>=1.0.9,<2.0.0)
Requires-Dist: django (>=5.0)
Requires-Dist: django-allauth[mfa,socialaccount] (>=65.11.2,<66.0.0)
Requires-Dist: django-bootstrap5 (>=23.3)
Requires-Dist: django-ckeditor-5 (>=0.2.13,<0.3.0)
Requires-Dist: django-cookie-consent (>=0.6.0,<0.7.0)
Requires-Dist: django-csp (>=4.0,<5.0)
Requires-Dist: django-minio-storage (>=0.5.7,<0.6.0)
Requires-Dist: django-pipeline (>=4.1.0,<5.0.0)
Requires-Dist: django-postman (>=4.5,<5.0)
Requires-Dist: django-prometheus (>=2.4.1,<3.0.0)
Requires-Dist: django-prose-editor (>=0.18.3,<0.19.0)
Requires-Dist: django-recaptcha (>=4.1.0,<5.0.0)
Requires-Dist: django-redis (>=6.0.0,<7.0.0)
Requires-Dist: django-redis-sessions (>=0.6.2,<0.7.0)
Requires-Dist: django-tinymce (>=4.1.0,<5.0.0)
Requires-Dist: fido2 (>=2.0.0,<3.0.0)
Requires-Dist: jsmin (>=3.0.1,<4.0.0)
Requires-Dist: lxml-html-clean (>=0.4.1,<0.5.0)
Requires-Dist: nh3 (>=0.3.0,<0.4.0)
Requires-Dist: psycopg (>=3.2.10,<4.0.0)
Requires-Dist: redis (>=6.4.0,<7.0.0)
Requires-Dist: uvicorn-worker (>=0.3.0,<0.4.0)
Project-URL: Documentation, https://github.com/d9pouces/df_site
Project-URL: Repository, https://github.com/d9pouces/df_site
